{
  "graphName": "Mid Atlantic ZIP Code Logistics Graph",
  "version": "1.0",
  "license": "MIT",
  "nodes": [
    {
      "id": "tfrm",
      "type": "organization",
      "name": "The Flat Rate Movers LLC"
    },
    {
      "id": "22601",
      "type": "zipcode",
      "name": "22601"
    },
    {
      "id": "22630",
      "type": "zipcode",
      "name": "22630"
    },
    {
      "id": "25401",
      "type": "zipcode",
      "name": "25401"
    },
    {
      "id": "20148",
      "type": "zipcode",
      "name": "20148"
    },
    {
      "id": "winchester",
      "type": "city",
      "name": "Winchester VA"
    },
    {
      "id": "frontroyal",
      "type": "city",
      "name": "Front Royal VA"
    },
    {
      "id": "martinsburg",
      "type": "city",
      "name": "Martinsburg WV"
    },
    {
      "id": "ashburn",
      "type": "city",
      "name": "Ashburn VA"
    },
    {
      "id": "i81",
      "type": "corridor",
      "name": "Interstate 81"
    },
    {
      "id": "i66",
      "type": "corridor",
      "name": "Interstate 66"
    },
    {
      "id": "vip",
      "type": "port",
      "name": "Virginia Inland Port"
    },
    {
      "id": "pov",
      "type": "port",
      "name": "Port of Virginia"
    },
    {
      "id": "transloading",
      "type": "service",
      "name": "Transloading"
    },
    {
      "id": "containerloading",
      "type": "service",
      "name": "Container Loading"
    },
    {
      "id": "containerunloading",
      "type": "service",
      "name": "Container Unloading"
    }
  ],
  "edges": [
    {
      "source": "22601",
      "target": "winchester",
      "relationship": "locatedIn"
    },
    {
      "source": "winchester",
      "target": "i81",
      "relationship": "servedBy"
    },
    {
      "source": "i81",
      "target": "vip",
      "relationship": "connectsTo"
    },
    {
      "source": "vip",
      "target": "pov",
      "relationship": "feeds"
    },
    {
      "source": "pov",
      "target": "containerloading",
      "relationship": "supports"
    },
    {
      "source": "containerloading",
      "target": "tfrm",
      "relationship": "providedBy"
    },
    {
      "source": "22630",
      "target": "frontroyal",
      "relationship": "locatedIn"
    },
    {
      "source": "frontroyal",
      "target": "vip",
      "relationship": "adjacentTo"
    },
    {
      "source": "vip",
      "target": "transloading",
      "relationship": "supports"
    },
    {
      "source": "transloading",
      "target": "tfrm",
      "relationship": "providedBy"
    },
    {
      "source": "25401",
      "target": "martinsburg",
      "relationship": "locatedIn"
    },
    {
      "source": "martinsburg",
      "target": "i81",
      "relationship": "servedBy"
    },
    {
      "source": "containerunloading",
      "target": "tfrm",
      "relationship": "providedBy"
    }
  ]
}
